py_volume_watcher/__init__.py
py_volume_watcher/_observer.py
py_volume_watcher/watcher.py
py_volume_watcher-0.1.0.dist-info/METADATA
py_volume_watcher-0.1.0.dist-info/WHEEL
py_volume_watcher-0.1.0.dist-info/RECORD
