Metadata-Version: 2.1
Name: py-volume-watcher
Version: 0.1.0
Summary: 
Author: Nicolas M.
Author-email: mine.nicolas@gmail.com
Requires-Python: >=3.10,<4.0
Classifier: Programming Language :: Python :: 3
Classifier: Programming Language :: Python :: 3.10
Classifier: Programming Language :: Python :: 3.11
